gather/__init__.py
gather/api.py
gather/commands.py
gather/entry.py
gather/example/__init__.py
gather/example/__main__.py
gather/example/breakfast.py
gather/example/main.py
gather/tests/__init__.py
gather/tests/_helper.py
gather/tests/cannot_be_imported.py
gather/tests/test_api.py
gather/tests/test_commands.py
gather/tests/test_entry.py
gather/tests/test_init.py
gather-2024.1.19.74288.dist-info/METADATA
gather-2024.1.19.74288.dist-info/WHEEL
gather-2024.1.19.74288.dist-info/entry_points.txt
gather-2024.1.19.74288.dist-info/top_level.txt
gather-2024.1.19.74288.dist-info/RECORD
