Metadata-Version: 2.1
Name: gather
Version: 2024.1.19.74288
Summary: A gatherer
Author-email: Moshe Zadka <moshez@zadka.club>
License: Permission is hereby granted, free of charge, to any person obtaining a
Project-URL: Homepage, https://github.com/elcaminoreal/gather
Project-URL: Development, https://github.com/elcaminoreal/gather
Project-URL: Documentation, https://gather.readthedocs.io/en/latest/
Project-URL: Blog, https://gather.works
Requires-Python: >=3.11
Requires-Dist: attrs
Requires-Dist: incremental
Requires-Dist: venusian
Requires-Dist: toolz
Requires-Dist: commander-data
Provides-Extra: doc
Requires-Dist: sphinx ; extra == 'doc'
Provides-Extra: docs
Requires-Dist: sphinx ; extra == 'docs'
Provides-Extra: lint
Requires-Dist: flake8 ; extra == 'lint'
Requires-Dist: black ; extra == 'lint'
Requires-Dist: pylint ; extra == 'lint'
Provides-Extra: mypy
Requires-Dist: mypy ; extra == 'mypy'
Provides-Extra: test
Requires-Dist: coverage ; extra == 'test'
Requires-Dist: virtue ; extra == 'test'
Provides-Extra: tests
Requires-Dist: virtue ; extra == 'tests'
Requires-Dist: pyhamcrest ; extra == 'tests'
Requires-Dist: coverage[toml] ; extra == 'tests'
